
---
title: 09丨数据交换的时候不推荐使用中间变量
date: 2020-04-09 21:01:07
tags:
- python
- 编写高质量代码91个建议
categories:
- python
---


```python
from timeit import Timer

print(Timer('temp = x;x = y;y = temp', 'x=2;y=3').timeit())

print(Timer('x, y = y, x', 'x=2;y=3').timeit())

```

    0.03795892000198364
    0.03163973399205133


表达式赋值是从右到左,对于x,y=y,x,在内存中:
1. 创建元祖(y,x), 其标识符和值分别为y,x及其对应的值.
2. 计算表达式左边的值并进行赋值,元组被依次分配给左边的标识符,通过解压unpacking.赋值交换.


```python
import dis

def swap1():
    x = 2
    y = 3
    x, y = y, x

def swap2():
    x = 2
    y = 3
    temp = x
    x = y
    y = temp

print("swap1():")
dis.dis(swap1)
print("swap2():")
dis.dis(swap2)
```

    swap1():
      4           0 LOAD_CONST               1 (2)
                  2 STORE_FAST               0 (x)
    
      5           4 LOAD_CONST               2 (3)
                  6 STORE_FAST               1 (y)
    
      6           8 LOAD_FAST                1 (y)
                 10 LOAD_FAST                0 (x)
                 12 ROT_TWO
                 14 STORE_FAST               0 (x)
                 16 STORE_FAST               1 (y)
                 18 LOAD_CONST               0 (None)
                 20 RETURN_VALUE
    swap2():
      9           0 LOAD_CONST               1 (2)
                  2 STORE_FAST               0 (x)
    
     10           4 LOAD_CONST               2 (3)
                  6 STORE_FAST               1 (y)
    
     11           8 LOAD_FAST                0 (x)
                 10 STORE_FAST               2 (temp)
    
     12          12 LOAD_FAST                1 (y)
                 14 STORE_FAST               0 (x)
    
     13          16 LOAD_FAST                2 (temp)
                 18 STORE_FAST               1 (y)
                 20 LOAD_CONST               0 (None)
                 22 RETURN_VALUE



```python

```
